typecaster/__init__.py
typecaster/models.py
typecaster/ssml.py
typecaster/utils.py
typecaster-0.1.0.dist-info/DESCRIPTION.rst
typecaster-0.1.0.dist-info/METADATA
typecaster-0.1.0.dist-info/RECORD
typecaster-0.1.0.dist-info/WHEEL
typecaster-0.1.0.dist-info/metadata.json
typecaster-0.1.0.dist-info/top_level.txt
