Metadata-Version: 2.0
Name: typecaster
Version: 0.1.0
Summary: Dynamically generate podcasts from text.
Home-page: https://github.com/nbedi/typecaster
Author: Neil Bedi
Author-email: neilbedi@gmail.com
License: MIT
Keywords: podcast
Platform: UNKNOWN
Classifier: Development Status :: 4 - Beta
Classifier: Topic :: Software Development :: Libraries :: Python Modules
Requires-Dist: apscheduler (>=3.0.5)
Requires-Dist: pydub (>=0.16.0)
Requires-Dist: requests (>=2.9.1)
Requires-Dist: responses (>=0.5.0)
Requires-Dist: six (>=1.6.1)
